topsis_AJ/__init__.py
topsis_AJ-0.0.1.dist-info/LICENSE
topsis_AJ-0.0.1.dist-info/METADATA
topsis_AJ-0.0.1.dist-info/WHEEL
topsis_AJ-0.0.1.dist-info/top_level.txt
topsis_AJ-0.0.1.dist-info/RECORD
