Metadata-Version: 2.1
Name: topsis-AJ
Version: 0.0.1
Summary: implementation of TOPSIS
Home-page: https://github.com/Amrit054/TOPSIS-amrit-101803089
Author: Amrit Jain
Author-email: ajain1_be18@thapar.edu
License: UNKNOWN
Platform: UNKNOWN
Classifier: Programming Language :: Python :: 3
Classifier: License :: OSI Approved :: MIT License
Classifier: Operating System :: OS Independent
